wolframclient/__init__.py
wolframclient/__main__.py
wolframclient/about.py
wolframclient/exception.py
wolframclient/settings.py
wolframclient/cli/__init__.py
wolframclient/cli/dispatch.py
wolframclient/cli/utils.py
wolframclient/cli/commands/__init__.py
wolframclient/cli/commands/benchmark.py
wolframclient/cli/commands/refactor.py
wolframclient/cli/commands/setup.py
wolframclient/cli/commands/start_externalevaluate.py
wolframclient/cli/commands/test.py
wolframclient/deserializers/__init__.py
wolframclient/deserializers/wxf/__init__.py
wolframclient/deserializers/wxf/wxfconsumer.py
wolframclient/deserializers/wxf/wxfparser.py
wolframclient/evaluation/__init__.py
wolframclient/evaluation/base.py
wolframclient/evaluation/pool.py
wolframclient/evaluation/result.py
wolframclient/evaluation/cloud/__init__.py
wolframclient/evaluation/cloud/asynccloudsession.py
wolframclient/evaluation/cloud/asyncoauth.py
wolframclient/evaluation/cloud/base.py
wolframclient/evaluation/cloud/cloudsession.py
wolframclient/evaluation/cloud/oauth.py
wolframclient/evaluation/cloud/request_adapter.py
wolframclient/evaluation/cloud/server.py
wolframclient/evaluation/kernel/__init__.py
wolframclient/evaluation/kernel/asyncsession.py
wolframclient/evaluation/kernel/initkernel.m
wolframclient/evaluation/kernel/kernelcontroller.py
wolframclient/evaluation/kernel/localsession.py
wolframclient/evaluation/kernel/zmqsocket.py
wolframclient/language/__init__.py
wolframclient/language/array.py
wolframclient/language/decorators.py
wolframclient/language/exceptions.py
wolframclient/language/expression.py
wolframclient/language/side_effects.py
wolframclient/language/traceback.py
wolframclient/serializers/__init__.py
wolframclient/serializers/base.py
wolframclient/serializers/encoder.py
wolframclient/serializers/serializable.py
wolframclient/serializers/utils.py
wolframclient/serializers/wl.py
wolframclient/serializers/wxf.py
wolframclient/serializers/encoders/__init__.py
wolframclient-1.1.10.dist-info/LICENSE
wolframclient-1.1.10.dist-info/METADATA
wolframclient-1.1.10.dist-info/WHEEL
wolframclient-1.1.10.dist-info/top_level.txt
wolframclient-1.1.10.dist-info/RECORD
