Metadata-Version: 2.1
Name: wolframclient
Version: 1.1.10
Summary: A Python library with various tools to interact with the Wolfram Language and the Wolfram Cloud.
Home-page: https://www.wolfram.com/
Author: Wolfram Research
Author-email: support@wolfram.com, dorianb@wolfram.com, riccardod@wolfram.com
License: MIT
Project-URL: Source code, https://github.com/WolframResearch/WolframClientForPython
Project-URL: Documentation, https://wolfr.am/wolframclientdoc
Project-URL: Wolfram Research, https://www.wolfram.com
Keywords: Wolfram Language,Wolfram Desktop,Mathematica,parser,serializer,WXF
Classifier: License :: OSI Approved :: MIT License
Classifier: Programming Language :: Python
Classifier: Programming Language :: Python :: 3
Classifier: Programming Language :: Python :: 3.5
Classifier: Programming Language :: Python :: 3.6
Classifier: Programming Language :: Python :: 3.7
Classifier: Topic :: Software Development :: Libraries
Requires-Python: >=3.5.3
License-File: LICENSE
Requires-Dist: numpy
Requires-Dist: pytz
Requires-Dist: requests
Requires-Dist: aiohttp
Requires-Dist: oauthlib
Requires-Dist: pyzmq
Requires-Dist: certifi >=2017.4.17
